tacl/__init__.py
tacl/__main__.py
tacl/catalogue.py
tacl/colour.py
tacl/constants.py
tacl/corpus.py
tacl/data_store.py
tacl/decorators.py
tacl/exceptions.py
tacl/highlighter.py
tacl/jitc.py
tacl/lifetime_report.py
tacl/normaliser.py
tacl/report.py
tacl/results.py
tacl/sequence.py
tacl/splitter.py
tacl/statistics_report.py
tacl/stripper.py
tacl/tei_corpus.py
tacl/text.py
tacl/tokenizer.py
tacl/work_joiner.py
tacl/assets/results_highlight/heatmap.js
tacl/assets/templates/lifetime.html
tacl/assets/templates/ngram_highlight.html
tacl/assets/templates/results_highlight.html
tacl/assets/templates/sequence.html
tacl/assets/xslt/CBETA_T0062_rest.xsl
tacl/assets/xslt/CBETA_T0220_reparent_divs.xsl
tacl/assets/xslt/CBETA_T0418_fix_verse.xsl
tacl/assets/xslt/CBETA_extract_commentary.xsl
tacl/assets/xslt/CBETA_extract_div.xsl
tacl/assets/xslt/CBETA_extract_verse.xsl
tacl/assets/xslt/CBETA_remove_divs.xsl
tacl/assets/xslt/prepare_tei_cbeta_github.xsl
tacl/assets/xslt/strip_tei.xsl
tacl/cli/__init__.py
tacl/cli/formatters.py
tacl/cli/utils.py
tacl-5.3.0.dist-info/LICENCE
tacl-5.3.0.dist-info/METADATA
tacl-5.3.0.dist-info/WHEEL
tacl-5.3.0.dist-info/entry_points.txt
tacl-5.3.0.dist-info/top_level.txt
tacl-5.3.0.dist-info/RECORD
