Metadata-Version: 2.1
Name: tacl
Version: 5.3.0
Summary: Text analyser for corpus linguistics
Author-email: Jamie Norrish <jamie@artefact.org.nz>
License: GNU GENERAL PUBLIC LICENSE
Project-URL: homepage, https://github.com/ajenhl/tacl
Project-URL: documentation, http://tacl.readthedocs.io/en/latest/
Classifier: Development Status :: 5 - Production/Stable
Classifier: Environment :: Console
Classifier: License :: OSI Approved :: GNU General Public License v3 or later (GPLv3+)
Classifier: Programming Language :: Python :: 3
Classifier: Topic :: Text Processing :: Linguistic
Requires-Python: >=3.8
License-File: LICENCE
Requires-Dist: biopython >=1.80
Requires-Dist: colorlog
Requires-Dist: Jinja2 >3.1.0
Requires-Dist: lxml
Requires-Dist: pandas
